cool_urls/__init__.py
cool_urls/admin.py
cool_urls/apps.py
cool_urls/coolers/__init__.py
cool_urls/coolers/base.py
cool_urls/coolers/exceptions.py
cool_urls/coolers/files.py
cool_urls/coolers/pages.py
cool_urls/coolers/videos.py
cool_urls/logging.py
cool_urls/management/commands/check_cool_urls.py
cool_urls/management/commands/cool_url.py
cool_urls/management/commands/cool_urls.py
cool_urls/management/commands/scratch.py
cool_urls/migrations/0001_initial.py
cool_urls/migrations/__init__.py
cool_urls/models.py
cool_urls/signals.py
cool_urls/templates/cool_urls/videos/local.html
cool_urls/templates/cool_urls/videos/remote/default.html
cool_urls/templates/cool_urls/videos/remote/vimeo.html
cool_urls/templates/cool_urls/videos/remote/youtube.html
cool_urls/templatetags/__init__.py
cool_urls/templatetags/cool_urls.py
cool_urls/tests/__init__.py
cool_urls/tests/coolers/__init__.py
cool_urls/tests/coolers/test_base.py
cool_urls/tests/coolers/test_files.py
cool_urls/tests/coolers/test_pages.py
cool_urls/tests/coolers/test_videos.py
cool_urls/tests/management/__init__.py
cool_urls/tests/management/commands/__init__.py
cool_urls/tests/management/commands/test_check_cool_urls.py
cool_urls/tests/management/commands/test_cool_url.py
cool_urls/tests/test_admin.py
cool_urls/tests/test_functional.py
cool_urls/tests/test_models.py
cool_urls/tests/test_templatetags.py
django_cool_urls-0.2.1.dist-info/LICENSE
django_cool_urls-0.2.1.dist-info/METADATA
django_cool_urls-0.2.1.dist-info/WHEEL
django_cool_urls-0.2.1.dist-info/RECORD
