Metadata-Version: 2.1
Name: django-cool-urls
Version: 0.2.1
Summary: Freeze outgoing links in time so that your site never 404s on external pages
License: GPL-3.0-or-later
Author: Daniel Quinn
Author-email: code@danielquinn.org
Requires-Python: >=3.11,<4.0
Classifier: License :: OSI Approved :: GNU General Public License v3 or later (GPLv3+)
Classifier: Programming Language :: Python :: 3
Classifier: Programming Language :: Python :: 3.11
Classifier: Programming Language :: Python :: 3.12
Provides-Extra: embed
Requires-Dist: Django (>=3.2)
Requires-Dist: httpx (>=0.27.0,<0.28.0)
Requires-Dist: yt-dlp ; extra == "embed"
